deep_t2i/__init__.py
deep_t2i/_nbdev.py
deep_t2i/constants.py
deep_t2i/data_anime_heads.py
deep_t2i/data_birds.py
deep_t2i/inference_anime_heads.py
deep_t2i/inference_birds.py
deep_t2i/model_anime_heads.py
deep_t2i/model_birds.py
deep_t2i/model_core.py
deep_t2i/torch_utils.py
deep_t2i/trainer.py
deep_t2i-0.0.1.dist-info/LICENSE
deep_t2i-0.0.1.dist-info/METADATA
deep_t2i-0.0.1.dist-info/WHEEL
deep_t2i-0.0.1.dist-info/entry_points.txt
deep_t2i-0.0.1.dist-info/top_level.txt
deep_t2i-0.0.1.dist-info/RECORD
