Metadata-Version: 2.1
Name: deep-t2i
Version: 0.0.1
Summary: My Experiments of Text to Image by Deep Learning
Home-page: https://github.com/cwza/deep_t2i/tree/master/
Author: cwza
Author-email: cwz0205a@gmail.com
License: Apache Software License 2.0
Keywords: None
Platform: UNKNOWN
Classifier: Development Status :: 3 - Alpha
Classifier: Intended Audience :: Developers
Classifier: License :: OSI Approved :: Apache Software License
Classifier: Natural Language :: English
Classifier: Programming Language :: Python :: 3.6
Classifier: Programming Language :: Python :: 3.7
Classifier: Programming Language :: Python :: 3.8
Requires-Python: >=3.6
Requires-Dist: matplotlib
Requires-Dist: pandas
Requires-Dist: pillow
Requires-Dist: kornia
Requires-Dist: transformers
Requires-Dist: scikit-learn
Requires-Dist: fastcore
Provides-Extra: dev
Requires-Dist: gdown ; extra == 'dev'
Requires-Dist: twine ; extra == 'dev'
Requires-Dist: nbdev ; extra == 'dev'
